chatWrapper/__init__.py
chatWrapper/new_chat.py
chatWrapper/new_chat_auth.py
chatWrapper-0.1.dist-info/METADATA
chatWrapper-0.1.dist-info/RECORD
chatWrapper-0.1.dist-info/WHEEL
chatWrapper-0.1.dist-info/top_level.txt
