Metadata-Version: 2.1
Name: chatWrapper
Version: 0.1
Summary: Wrapper for Chat API: https://os-chat-api.herokuapp.com/
Home-page: https://github.com/duggalrd/chat_api_wrapper
Author: Rahul Duggal
Author-email: duggalr42@gmail.com
License: MIT
Platform: UNKNOWN
